ringsage/evaluate.py
ringsage/model.py
ringsage/ringsageconv/cycle_detection.py
ringsage/ringsageconv/layer.py
ringsage/schemas.py
ringsage/train.py
ringsage/types.py
ringsage/utils.py
ringsage-0.1.1.dist-info/LICENSE
ringsage-0.1.1.dist-info/METADATA
ringsage-0.1.1.dist-info/WHEEL
ringsage-0.1.1.dist-info/RECORD
