Metadata-Version: 2.1
Name: ringsage
Version: 0.1.1
Summary: 
Author: Herumb Shandilya
Author-email: herumbshandilya123@gmail.com
Requires-Python: >=3.10,<4.0
Classifier: Programming Language :: Python :: 3
Classifier: Programming Language :: Python :: 3.10
Classifier: Programming Language :: Python :: 3.11
Classifier: Programming Language :: Python :: 3.12
Requires-Dist: datasets (>=3.1.0,<4.0.0)
Requires-Dist: logger (>=1.4,<2.0)
Requires-Dist: networkx (>=3.4.2,<4.0.0)
Requires-Dist: pydantic (>=2.10.3,<3.0.0)
Requires-Dist: pyright (>=1.1.390,<2.0.0)
Requires-Dist: torch (>=2.5.1,<3.0.0)
Requires-Dist: torch-geometric (>=2.6.1,<3.0.0)
Requires-Dist: transformers (>=4.46.3,<5.0.0)
